termix/__init__.py
termix/termix.py
termix-0.0.2.dist-info/METADATA
termix-0.0.2.dist-info/WHEEL
termix-0.0.2.dist-info/licenses/LICENSE
termix-0.0.2.dist-info/RECORD
