Metadata-Version: 2.3
Name: termix
Version: 0.0.2
Summary: A small base class for Terminal App
Project-URL: Developer, https://armedjuror.in
Author-email: Armed Juror <armedjuror@gmail.com>
License-File: LICENSE
Classifier: License :: OSI Approved :: MIT License
Classifier: Operating System :: OS Independent
Classifier: Programming Language :: Python :: 3
Requires-Python: >=3.8
